cpa/__init__.py
cpa/cli.py
cpa/project.py
cpa/pylintrc
cpa-0.4.1.dist-info/LICENSE
cpa-0.4.1.dist-info/METADATA
cpa-0.4.1.dist-info/WHEEL
cpa-0.4.1.dist-info/entry_points.txt
cpa-0.4.1.dist-info/top_level.txt
cpa-0.4.1.dist-info/RECORD
