Metadata-Version: 2.1
Name: cpa
Version: 0.4.1
Summary: full life cycle management for python apps and libs
Home-page: https://github.com/FlorianLudwig/cpa
Author: Florian Ludwig
Author-email: f.ludwig@greyrook.com
License: Apache Software License 2.0
Keywords: cpa
Platform: UNKNOWN
Classifier: Development Status :: 2 - Pre-Alpha
Classifier: Intended Audience :: Developers
Classifier: License :: OSI Approved :: Apache Software License
Classifier: Natural Language :: English
Classifier: Programming Language :: Python :: 3
Classifier: Programming Language :: Python :: 3.7
Requires-Dist: Click (>=6.0)
Requires-Dist: tomlkit
Requires-Dist: setuptools
